dtuprosys/__init__.py
dtuprosys/chemometrics/__init__.py
dtuprosys/chemometrics/datasets/__init__.py
dtuprosys/chemometrics/datasets/_base.py
dtuprosys/chemometrics/datasets/data/__init__.py
dtuprosys/chemometrics/datasets/data/fermentation_hplc.csv
dtuprosys/chemometrics/datasets/data/fermentation_spectra.csv
dtuprosys/chemometrics/datasets/data/train_hplc.csv
dtuprosys/chemometrics/datasets/data/train_spectra.csv
dtuprosys/chemometrics/modelling/__init__.py
dtuprosys/chemometrics/modelling/cross_validation.py
dtuprosys/chemometrics/plotting/__init__.py
dtuprosys/chemometrics/plotting/plot_fermentation.py
dtuprosys/chemometrics/plotting/plot_predictions.py
dtuprosys/chemometrics/plotting/plot_spectra.py
dtuprosys/chemometrics/preprocessing/__init__.py
dtuprosys/chemometrics/preprocessing/preprocessing.py
tests/__init__.py
tests/test_loadings.py
tests/test_preprocessing.py
dtuprosys-0.1.24.dist-info/LICENSE
dtuprosys-0.1.24.dist-info/METADATA
dtuprosys-0.1.24.dist-info/WHEEL
dtuprosys-0.1.24.dist-info/top_level.txt
dtuprosys-0.1.24.dist-info/RECORD
