Metadata-Version: 2.1
Name: dtuprosys
Version: 0.1.24
Summary: Package to teach chemometrics in the context of fermentation processes
Home-page: https://github.com/paucablop/dtu.prosys
Author: Pau Cabaneros
Author-email: pau.cabaneros@gmail.com
Project-URL: Bug Tracker, https://github.com/paucablop/dtu.prosys/issues/
Classifier: Programming Language :: Python :: 3
Classifier: License :: OSI Approved :: MIT License
Classifier: Operating System :: OS Independent
Requires-Python: >=3.7
License-File: LICENSE
Requires-Dist: numpy
Requires-Dist: pandas
Requires-Dist: matplotlib
Requires-Dist: mbpls
Requires-Dist: scipy
Requires-Dist: scikit-learn
